class_examples/systemx.v
module systemx
	(output wire F,
	input wire A, B, C);

	wire An, Bn, Cn;
	wire m0, m2,m6;

	assign An = ~A;
	assign Bn = ~B;
	assign Cn = ~C;

	assign m0 = An & Bn & Cn;
	assign m2 = An & B & Cn;
	assign m6 = A & B & Cn;

	assign F = m0 | m2 | m6;
	
endmodule

class_examples/systemx_tb.v
`timescale 1ns/1ps

module systemx_tb();

	reg A_TB, B_TB, C_TB;
	wire F_TB;

	systemx DUT(.F(F_TB), .A(A_TB), .B(B_TB), .C(C_TB));

	initial
		begin
		
			$dumpfile("systemx_tb.vcd");
			$dumpvars(0,systemx_tb);
		
			    A_TB=0; B_TB=0; C_TB=0;
			#10 A_TB=0; B_TB=0; C_TB=1;
			#10 A_TB=0; B_TB=1; C_TB=0;
			#10 A_TB=0; B_TB=1; C_TB=1;
			#10 A_TB=1; B_TB=0; C_TB=0;
			#10 A_TB=1; B_TB=0; C_TB=1;
			#10 A_TB=1; B_TB=1; C_TB=0;
			#10 A_TB=1; B_TB=1; C_TB=1;
			#10 A_TB=0; B_TB=0; C_TB=0;
		end

endmodule

class_examples/systemx_tb.vcd
$date
	Sun Mar 21 14:35:48 2021
$end
$version
	Icarus Verilog
$end
$timescale
	1ps
$end
$scope module systemx_tb $end
$var wire 1 ! F_TB $end
$var reg 1 " A_TB $end
$var reg 1 # B_TB $end
$var reg 1 $ C_TB $end
$scope module DUT $end
$var wire 1 " A $end
$var wire 1 % An $end
$var wire 1 # B $end
$var wire 1 & Bn $end
$var wire 1 $ C $end
$var wire 1 ' Cn $end
$var wire 1 ! F $end
$var wire 1 ( m0 $end
$var wire 1 ) m2 $end
$var wire 1 * m6 $end
$upscope $end
$upscope $end
$enddefinitions $end
#0
$dumpvars
0*
0)
1(
1'
1&
1%
0$
0#
0"
1!
$end
#10000
0!
0(
0'
1$
#20000
1!
1)
1'
0&
0$
1#
#30000
0!
0)
0'
1$
#40000
1'
1&
0%
0$
0#
1"
#50000
0'
1$
#60000
1!
1*
1'
0&
0$
1#
#70000
0!
0*
0'
1$
#80000
1!
1(
1'
1&
1%
0$
0#
0"
